pyrify/__init__.py
pyrify/cli.py
pyrify/drivers.py
pyrify/strategies.py
pyrify/types.py
pyrify/utils.py
pyrify/commands/__init__.py
pyrify/commands/init.py
pyrify/commands/sanitize.py
pyrify/commands/template.py
pyrify/templates/ckan_211.yml
pyrify/templates/drupal_10.yml
pyrify/tests/__init__.py
pyrify/tests/models.py
pyrify/tests/test_sanitize.py
pyrify-0.4.0.dist-info/licenses/LICENSE
pyrify-0.4.0.dist-info/METADATA
pyrify-0.4.0.dist-info/WHEEL
pyrify-0.4.0.dist-info/entry_points.txt
pyrify-0.4.0.dist-info/top_level.txt
pyrify-0.4.0.dist-info/RECORD
